viasp/__init__.py
viasp/__main__.py
viasp/api.py
viasp/clingoApiClient.py
viasp/exampleTransformer.py
viasp/exceptions.py
viasp/wrapper.py
viasp/asp/__init__.py
viasp/asp/ast_types.py
viasp/asp/justify.py
viasp/asp/recursion.py
viasp/asp/reify.py
viasp/asp/relax.py
viasp/asp/utils.py
viasp/locales/en.json
viasp/server/__init__.py
viasp/server/database.py
viasp/server/factory.py
viasp/server/models.py
viasp/server/startup.py
viasp/server/blueprints/__init__.py
viasp/server/blueprints/api.py
viasp/server/blueprints/app.py
viasp/server/blueprints/dag_api.py
viasp/shared/__init__.py
viasp/shared/clingo_stats.py
viasp/shared/defaults.py
viasp/shared/event.py
viasp/shared/interfaces.py
viasp/shared/io.py
viasp/shared/model.py
viasp/shared/simple_logging.py
viasp/shared/util.py
viasp_backend-2.3.0.post3.dist-info/licenses/LICENCE.md
viasp_backend-2.3.0.post3.dist-info/METADATA
viasp_backend-2.3.0.post3.dist-info/WHEEL
viasp_backend-2.3.0.post3.dist-info/entry_points.txt
viasp_backend-2.3.0.post3.dist-info/top_level.txt
viasp_backend-2.3.0.post3.dist-info/RECORD
